README
setup.py
datadeck/__init__.py
datadeck/main.py
datadeck/operations.py
datadeck/settings.py
datadeck.egg-info/PKG-INFO
datadeck.egg-info/SOURCES.txt
datadeck.egg-info/dependency_links.txt
datadeck.egg-info/entry_points.txt
datadeck.egg-info/not-zip-safe
datadeck.egg-info/requires.txt
datadeck.egg-info/top_level.txt
datadeck/gui/__init__.py
datadeck/gui/base.py
datadeck/gui/main.py
datadeck/gui/package.py
datadeck/gui/settings.py
datadeck/gui/util/__init__.py
datadeck/gui/util/console.py
datadeck/gui/util/download.py
datadeck/gui/util/operations.py
datadeck/gui/util/package.py
datadeck/gui/util/validator.py
datadeck/res/__init__.py