Metadata-Version: 1.0
Name: datadeck
Version: 0.4.0
Summary: DataDeck (dpm GUI): wxPython GUI for dpm: data packaging system and utilities
Home-page: http://task3.cc/projects/datadeck
Author: Daniel Graziotin
Author-email: d@danielgraziotin.it
License: Simplified BSD License
Keywords: data,packaging,component,tool,GUI
Platform: UNKNOWN
